jpy_sync_db_lite/__init__.py
jpy_sync_db_lite/__main__.py
jpy_sync_db_lite/db_engine.py
jpy_sync_db_lite/errors.py
jpy_sync_db_lite/sql_helper.py
jpy_sync_db_lite-2025.5.0.dist-info/licenses/LICENSE
jpy_sync_db_lite-2025.5.0.dist-info/METADATA
jpy_sync_db_lite-2025.5.0.dist-info/WHEEL
jpy_sync_db_lite-2025.5.0.dist-info/entry_points.txt
jpy_sync_db_lite-2025.5.0.dist-info/top_level.txt
jpy_sync_db_lite-2025.5.0.dist-info/RECORD
