Metadata-Version: 2.4
Name: jpy-sync-db-lite
Version: 2025.5.0
Summary: Jim's Python - Synchronous Database Wrapper for SQLite
Author: Jim Schilling
Maintainer: Jim Schilling
License-Expression: MIT
Project-URL: Homepage, https://github.com/jim-schilling/jpy-sync-db-lite
Project-URL: Repository, https://github.com/jim-schilling/jpy-sync-db-lite.git
Project-URL: Documentation, https://github.com/jim-schilling/jpy-sync-db-lite#readme
Project-URL: Bug Tracker, https://github.com/jim-schilling/jpy-sync-db-lite/issues
Project-URL: Changelog, https://github.com/jim-schilling/jpy-sync-db-lite/blob/main/CHANGELOG.md
Keywords: sqlite,database,synchronous,threading,sqlalchemy,orm
Classifier: Development Status :: 4 - Beta
Classifier: Intended Audience :: Developers
Classifier: Operating System :: OS Independent
Classifier: Programming Language :: Python :: 3
Classifier: Programming Language :: Python :: 3.10
Classifier: Programming Language :: Python :: 3.11
Classifier: Programming Language :: Python :: 3.12
Classifier: Programming Language :: Python :: Implementation :: CPython
Classifier: Topic :: Database
Classifier: Topic :: Database :: Database Engines/Servers
Classifier: Topic :: Software Development :: Libraries :: Python Modules
Classifier: Topic :: Software Development :: Libraries :: Application Frameworks
Classifier: Typing :: Typed
Requires-Python: >=3.10
License-File: LICENSE
Requires-Dist: sqlalchemy<3.0,>=2.0.37
Requires-Dist: sqlparse<1.0,>=0.4.0
Provides-Extra: dev
Requires-Dist: pytest<8.0,>=7.4.0; extra == "dev"
Requires-Dist: pytest-cov<5.0,>=4.1.0; extra == "dev"
Requires-Dist: pytest-mock<4.0,>=3.11.0; extra == "dev"
Requires-Dist: pytest-xdist<4.0,>=3.3.0; extra == "dev"
Requires-Dist: coverage[toml]<8.0,>=7.3.0; extra == "dev"
Requires-Dist: mypy<2.0,>=1.5.0; extra == "dev"
Requires-Dist: ruff<1.0,>=0.1.0; extra == "dev"
Requires-Dist: isort<6.0,>=5.12.0; extra == "dev"
Requires-Dist: bandit[toml]<2.0,>=1.7.0; extra == "dev"
Requires-Dist: pre-commit<4.0,>=3.4.0; extra == "dev"
Requires-Dist: types-setuptools<69.0,>=68.0.0; extra == "dev"
Provides-Extra: test
Requires-Dist: pytest<8.0,>=7.4.0; extra == "test"
Requires-Dist: pytest-cov<5.0,>=4.1.0; extra == "test"
Requires-Dist: pytest-mock<4.0,>=3.11.0; extra == "test"
Requires-Dist: pytest-xdist<4.0,>=3.3.0; extra == "test"
Requires-Dist: coverage[toml]<8.0,>=7.3.0; extra == "test"
Provides-Extra: lint
Requires-Dist: ruff<1.0,>=0.1.0; extra == "lint"
Requires-Dist: isort<6.0,>=5.12.0; extra == "lint"
Requires-Dist: bandit[toml]<2.0,>=1.7.0; extra == "lint"
Provides-Extra: type
Requires-Dist: mypy<2.0,>=1.5.0; extra == "type"
Requires-Dist: types-setuptools<69.0,>=68.0.0; extra == "type"
Dynamic: license-file
